{
 "creation": "2020-04-26 13:03:30.405135",
 "docstatus": 0,
 "doctype": "Onboarding",
 "idx": 0,
 "is_complete": 1,
 "is_skipped": 0,
 "modified": "2020-04-28 22:14:32.081565",
 "modified_by": "Administrator",
 "module": "Website",
 "name": "Website",
 "owner": "Administrator",
 "steps": [
  {
   "step": "Introduction to Website"
  },
  {
   "step": "Create Blogger"
  },
  {
   "step": "Add Blog Category"
  },
  {
   "step": "Set Website Theme"
  },
  {
   "step": "Enable Website Tracking"
  }
 ],
 "subtitle": "Blogs, website view tracking, and more.",
 "success_message": "Yayy! Your website is all setup!",
 "title": "Let's Setup Your Website",
 "user_can_dismiss": 1,
 "user_can_skip": 0
}